osds/__init__.py
osds/utils.py
osds_channel_preview-1.0.41.dist-info/LICENSE
osds_channel_preview-1.0.41.dist-info/METADATA
osds_channel_preview-1.0.41.dist-info/WHEEL
osds_channel_preview-1.0.41.dist-info/top_level.txt
osds_channel_preview-1.0.41.dist-info/RECORD
